{
    "2024-09-22 02:21:00": {
        "chinese": "秋高气爽",
        "pinyin": "qiū gāo qì shuǎng",
        "sino_vietnamese": "thu cao khí sảng",
        "vietnamese_meaning": "trời thu cao, khí trời trong lành"
    },
    "2024-09-22 02:21:28": {
        "chinese": "我喜欢旅行",
        "pinyin": "wǒ xǐhuān lǚxíng",
        "sino_vietnamese": "ngã hỉ hoan du lịch",
        "vietnamese_meaning": "tôi thích du lịch"
    },
    "2024-09-22 02:23:48": {
        "chinese": "今天天气很好",
        "pinyin": "jīntiān tiānqì hěn hǎo",
        "sino_vietnamese": "kim thiên thiên khí ngận hảo",
        "vietnamese_meaning": "hôm nay thời tiết rất tốt"
    }
}